dioptic/profileparser/__init__.py
dioptic/profileparser/profileparser.cp39-win_amd64.pyd
dioptic/profileparser/profileparser.pyi
dioptic/profileparser/py.typed
dioptic_profileparser-0.3.2.dist-info/METADATA
dioptic_profileparser-0.3.2.dist-info/WHEEL
dioptic_profileparser-0.3.2.dist-info/licenses/LICENSE
dioptic_profileparser-0.3.2.dist-info/RECORD
